{
  "id": "e7847c13-9521-444d-a68d-9e4cb13a6bda_asm",
  "marca": "LaesquinaRandom",
  "formato": "16:9",
  "tipo": "Largo",
  "inicio": "2026-06-15 20:42:10",
  "hooks": {
    "frases_recibidas": 23,
    "insertados": 11,
    "activos": true
  },
  "subtitulos": {
    "aplica": false,
    "bloques_habla": 0,
    "desplazado_por_hooks": false
  },
  "paquete": {
    "generado": true,
    "respaldo": false
  },
  "errores": [],
  "fin": "2026-06-15 21:48:55",
  "duracion_real_seg": 2524.5,
  "video_final": "00_FINAL_EXTREME_DYNAMICS.mp4"
}