{
  "id": "1905f390-1e61-4f2c-b069-d6c4c65aa510_asm",
  "marca": "La Viuda",
  "formato": "16:9",
  "tipo": "Largo",
  "inicio": "2026-07-01 18:31:24",
  "hooks": {
    "frases_recibidas": 23,
    "insertados": 7,
    "activos": true,
    "tiempos": [
      {
        "rehook_en_seg": 205.03,
        "pausa_mas_cercana_seg": 205.05,
        "distancia_seg": 0.01,
        "formato": "A"
      },
      {
        "rehook_en_seg": 359.5,
        "pausa_mas_cercana_seg": 359.67,
        "distancia_seg": 0.17,
        "formato": "A"
      },
      {
        "rehook_en_seg": 534.6,
        "pausa_mas_cercana_seg": 535.15,
        "distancia_seg": 0.55,
        "formato": "A"
      },
      {
        "rehook_en_seg": 721.73,
        "pausa_mas_cercana_seg": 722.34,
        "distancia_seg": 0.6,
        "formato": "A"
      },
      {
        "rehook_en_seg": 900.6,
        "pausa_mas_cercana_seg": 901.12,
        "distancia_seg": 0.52,
        "formato": "B"
      },
      {
        "rehook_en_seg": 1075.87,
        "pausa_mas_cercana_seg": 1076.8,
        "distancia_seg": 0.93,
        "formato": "B"
      }
    ],
    "pausas_voz_detectadas": [
      3.38,
      10.03,
      15.48,
      18.2,
      23.97,
      29.87,
      34.66,
      36.51,
      39.59,
      43.5,
      47.12,
      52.34,
      59.49,
      64.97,
      68.55,
      71.13,
      73.82,
      79.6,
      84.77,
      88.86,
      90.34,
      93.7,
      96.69,
      101.87,
      106.26,
      110.27,
      116.58,
      119.88,
      124.17,
      128.33,
      131.29,
      136.76,
      139.27,
      143.68,
      146.38,
      148.2,
      154.13,
      155.87,
      161.36,
      164.65,
      170.98,
      174.41,
      177.61,
      179.75,
      183.1,
      191.78,
      194.57,
      202.63,
      205.05,
      210.39,
      214.29,
      215.9,
      221.28,
      227.08,
      229.49,
      231.68,
      236.84,
      237.81,
      241.46,
      249.19,
      255.43,
      258.91,
      266.12,
      267.65,
      273.5,
      277.76,
      280.54,
      285.8,
      288.77,
      296.98,
      298.16,
      301.33,
      307.05,
      313.43,
      316.62,
      318.91,
      320.25,
      322.5,
      326.05,
      333.98,
      337.16,
      341.44,
      344.47,
      348.04,
      353.48,
      355.71,
      359.67,
      363.12,
      367.08,
      370.86,
      373.29,
      376.21,
      381.76,
      384.91,
      389.74,
      392.27,
      395.82,
      400.53,
      405.74,
      409.75,
      417.28,
      420.18,
      423.17,
      428.12,
      430.78,
      442.28,
      448.8,
      453.42,
      455.32,
      458.35,
      464.15,
      466.7,
      470.21,
      474.12,
      477.68,
      481.26,
      487.48,
      491.58,
      498.79,
      501.48,
      506.66,
      511.27,
      516.63,
      521.28,
      523.33,
      525.75,
      527.97,
      535.15,
      540.26,
      542.82,
      551.85,
      553.46,
      555.33,
      560.8,
      563.66,
      568.72,
      571.1,
      573.6,
      580.39,
      583.42,
      585.33,
      587.26,
      591.01,
      596.47,
      600.41,
      603.17,
      606.17,
      609.88,
      612.32,
      615.26,
      617.31,
      622.16,
      630.42,
      633.27,
      636.01,
      640.58,
      643.17,
      647.02,
      649.24,
      653.77,
      657.86,
      661.97,
      663.0,
      666.1,
      668.37,
      673.74,
      677.82,
      682.53,
      689.17,
      691.9,
      695.23,
      699.11,
      702.59,
      705.79,
      713.61,
      719.38,
      722.34,
      728.89,
      732.84,
      735.59,
      740.22,
      742.1,
      744.5,
      747.68,
      754.51,
      756.96,
      761.84,
      765.59,
      770.12,
      776.58,
      785.97,
      789.32,
      791.74,
      793.82,
      795.76,
      800.57,
      804.6,
      809.19,
      814.14,
      815.15,
      816.91,
      829.51,
      833.5,
      835.67,
      839.42,
      840.73,
      841.72,
      844.56,
      850.1,
      854.64,
      857.2,
      861.23,
      868.27,
      870.3,
      871.62,
      878.32,
      882.44,
      889.06,
      894.2,
      896.04,
      901.12,
      905.84,
      907.18,
      911.22,
      915.6,
      921.01,
      923.02,
      926.22,
      932.81,
      938.33,
      941.21,
      944.68,
      948.26,
      954.87,
      958.01,
      963.57,
      966.56,
      973.03,
      975.16,
      981.21,
      987.04,
      990.32,
      992.41,
      998.52,
      1000.76,
      1007.13,
      1011.7,
      1015.52,
      1019.99,
      1024.68,
      1027.93,
      1032.04,
      1034.23,
      1037.94,
      1042.28,
      1044.13,
      1048.48,
      1055.71,
      1062.25,
      1066.17,
      1071.09,
      1076.8,
      1078.78,
      1079.82,
      1082.72,
      1085.06,
      1096.31,
      1099.68,
      1105.95,
      1110.19,
      1114.07,
      1115.03,
      1118.89,
      1121.52,
      1123.73,
      1127.7,
      1131.21,
      1134.97,
      1138.95,
      1146.66,
      1150.12,
      1155.07,
      1158.66,
      1159.48,
      1161.31,
      1166.93,
      1169.08,
      1172.86,
      1175.08,
      1182.07,
      1188.97,
      1191.19,
      1194.32,
      1198.26,
      1201.97,
      1205.27,
      1209.41,
      1213.28,
      1216.64,
      1218.6,
      1221.54,
      1224.44,
      1229.82,
      1234.68,
      1237.66,
      1241.57,
      1247.2,
      1250.93,
      1255.23
    ],
    "hook_inicial_seg": 0.0
  },
  "subtitulos": {
    "aplica": false,
    "bloques_habla": 0,
    "desplazado_por_hooks": false
  },
  "paquete": {
    "generado": true,
    "respaldo": false
  },
  "errores": [],
  "fin": "2026-07-01 19:19:13",
  "duracion_real_seg": 1299.6,
  "video_final": "00_FINAL_EXTREME_DYNAMICS.mp4",
  "MEDICION_REAL": {
    "analisis_ffmpeg": "ok",
    "duracion_video_seg": 1299.6,
    "silencios_reales": [
      2.57,
      8.58,
      16.13,
      22.8,
      137.14,
      139.27,
      281.72,
      283.06,
      287.99,
      293.48,
      296.03,
      352.75,
      357.03,
      369.06,
      371.29,
      375.34,
      376.42,
      488.59,
      627.31,
      631.06,
      633.54,
      638.57,
      643.38,
      703.72,
      716.44,
      720.31,
      723.86,
      726.92,
      778.5,
      780.95,
      785.7,
      787.98,
      800.56,
      824.45,
      874.11,
      912.93,
      918.18,
      920.03,
      921.09,
      924.75,
      926.24,
      927.84,
      938.01,
      947.81,
      1013.83,
      1051.47,
      1054.73,
      1058.84,
      1061.03,
      1064.77,
      1070.89,
      1078.63,
      1088.98,
      1092.95,
      1188.23,
      1188.99,
      1190.89,
      1196.53,
      1198.62,
      1202.36,
      1204.65,
      1209.95,
      1218.47,
      1223.91,
      1227.95,
      1299.09
    ],
    "num_silencios_reales": 66,
    "cortes_escena_reales": [
      9.8,
      9.83,
      91.1,
      91.2,
      106.6,
      151.83,
      156.3,
      160.77,
      163.0,
      165.23,
      167.47,
      169.7,
      174.17,
      217.83,
      217.87,
      245.07,
      271.0,
      293.33,
      322.63,
      375.27,
      375.3,
      380.27,
      380.37,
      384.87,
      384.97,
      465.1,
      485.5,
      553.57,
      553.6,
      619.87,
      624.73,
      634.47,
      639.33,
      646.63,
      683.03,
      716.3,
      743.5,
      743.53,
      895.67,
      955.27,
      959.67,
      964.07,
      970.67,
      975.07,
      979.47,
      981.67,
      1008.0,
      1033.93,
      1059.13,
      1059.23,
      1063.73,
      1063.83,
      1068.33,
      1068.43,
      1072.93,
      1073.03,
      1151.3,
      1168.73,
      1191.1,
      1211.87
    ],
    "num_cortes_escena": 69,
    "rehooks_analisis": [
      {
        "escena": 9,
        "t_planeado": 205.03,
        "silencio_real_cercano": 139.27,
        "dist_a_pausa_real": 65.763,
        "corte_escena_real_cercano": 217.83,
        "dist_a_corte_real": 12.797,
        "EN_PAUSA": false
      },
      {
        "escena": 15,
        "t_planeado": 359.67,
        "silencio_real_cercano": 357.03,
        "dist_a_pausa_real": 2.636,
        "corte_escena_real_cercano": 375.27,
        "dist_a_corte_real": 15.604,
        "EN_PAUSA": false
      },
      {
        "escena": 21,
        "t_planeado": 535.15,
        "silencio_real_cercano": 488.59,
        "dist_a_pausa_real": 46.561,
        "corte_escena_real_cercano": 553.57,
        "dist_a_corte_real": 18.419,
        "EN_PAUSA": false
      },
      {
        "escena": 27,
        "t_planeado": 721.73,
        "silencio_real_cercano": 720.31,
        "dist_a_pausa_real": 1.423,
        "corte_escena_real_cercano": 716.3,
        "dist_a_corte_real": 5.433,
        "EN_PAUSA": false
      },
      {
        "escena": 33,
        "t_planeado": 900.6,
        "silencio_real_cercano": 912.93,
        "dist_a_pausa_real": 12.33,
        "corte_escena_real_cercano": 895.67,
        "dist_a_corte_real": 4.93,
        "EN_PAUSA": false
      },
      {
        "escena": 40,
        "t_planeado": 1076.8,
        "silencio_real_cercano": 1078.63,
        "dist_a_pausa_real": 1.83,
        "corte_escena_real_cercano": 1073.03,
        "dist_a_corte_real": 3.77,
        "EN_PAUSA": false
      }
    ],
    "rehooks_total": 6,
    "rehooks_fuera_de_pausa": 6,
    "VEREDICTO": "6 re-hook(s) FUERA de pausa",
    "silencios_que_uso_el_worker": [
      3.38,
      10.03,
      15.48,
      18.2,
      23.97,
      29.87,
      34.66,
      36.51,
      39.59,
      43.5,
      47.12,
      52.34,
      59.49,
      64.97,
      68.55,
      71.13,
      73.82,
      79.6,
      84.77,
      88.86,
      90.34,
      93.7,
      96.69,
      101.87,
      106.26,
      110.27,
      116.58,
      119.88,
      124.17,
      128.33,
      131.29,
      136.76,
      139.27,
      143.68,
      146.38,
      148.2,
      154.13,
      155.87,
      161.36,
      164.65,
      170.98,
      174.41,
      177.61,
      179.75,
      183.1,
      191.78,
      194.57,
      202.63,
      205.05,
      210.39,
      214.29,
      215.9,
      221.28,
      227.08,
      229.49,
      231.68,
      236.84,
      237.81,
      241.46,
      249.19
    ]
  }
}