[
  {
    "ts": "2026-06-14 09:33:32",
    "donde": "lanzar_orden_motor",
    "error": "Traceback (most recent call last):\n  File \"/opt/render/project/src/app.py\", line 1084, in api_lanzar_orden_motor\n    tid = _disparar_orden_interna(marca, formato, \"\", duracion_min)\n          ^^^^^^^^^^^^^^^^^^^^^^^^^^^^^^^^^^^^^^^^^^^^^^^^^^^^^^^^^\n  File \"/opt/render/project/src/app.py\", line 506, in _disparar_orden_interna\n    raise Exception(resultado[:120])\nException: ERROR CRÍTICO API GEMINI:\n\n"
  },
  {
    "ts": "2026-06-14 09:34:05",
    "donde": "lanzar_orden_motor",
    "error": "Traceback (most recent call last):\n  File \"/opt/render/project/src/app.py\", line 1084, in api_lanzar_orden_motor\n    tid = _disparar_orden_interna(marca, formato, \"\", duracion_min)\n          ^^^^^^^^^^^^^^^^^^^^^^^^^^^^^^^^^^^^^^^^^^^^^^^^^^^^^^^^^\n  File \"/opt/render/project/src/app.py\", line 506, in _disparar_orden_interna\n    raise Exception(resultado[:120])\nException: ERROR CRÍTICO API GEMINI:\n\n"
  },
  {
    "ts": "2026-06-14 09:34:38",
    "donde": "lanzar_orden_motor",
    "error": "Traceback (most recent call last):\n  File \"/opt/render/project/src/app.py\", line 1084, in api_lanzar_orden_motor\n    tid = _disparar_orden_interna(marca, formato, \"\", duracion_min)\n          ^^^^^^^^^^^^^^^^^^^^^^^^^^^^^^^^^^^^^^^^^^^^^^^^^^^^^^^^^\n  File \"/opt/render/project/src/app.py\", line 506, in _disparar_orden_interna\n    raise Exception(resultado[:120])\nException: ERROR CRÍTICO API GEMINI:\n\n"
  },
  {
    "ts": "2026-06-14 09:35:11",
    "donde": "lanzar_orden_motor",
    "error": "Traceback (most recent call last):\n  File \"/opt/render/project/src/app.py\", line 1084, in api_lanzar_orden_motor\n    tid = _disparar_orden_interna(marca, formato, \"\", duracion_min)\n          ^^^^^^^^^^^^^^^^^^^^^^^^^^^^^^^^^^^^^^^^^^^^^^^^^^^^^^^^^\n  File \"/opt/render/project/src/app.py\", line 506, in _disparar_orden_interna\n    raise Exception(resultado[:120])\nException: ERROR CRÍTICO API GEMINI:\n\n"
  },
  {
    "ts": "2026-06-14 09:35:44",
    "donde": "lanzar_orden_motor",
    "error": "Traceback (most recent call last):\n  File \"/opt/render/project/src/app.py\", line 1084, in api_lanzar_orden_motor\n    tid = _disparar_orden_interna(marca, formato, \"\", duracion_min)\n          ^^^^^^^^^^^^^^^^^^^^^^^^^^^^^^^^^^^^^^^^^^^^^^^^^^^^^^^^^\n  File \"/opt/render/project/src/app.py\", line 506, in _disparar_orden_interna\n    raise Exception(resultado[:120])\nException: ERROR CRÍTICO API GEMINI:\n\n"
  },
  {
    "ts": "2026-06-14 09:36:17",
    "donde": "lanzar_orden_motor",
    "error": "Traceback (most recent call last):\n  File \"/opt/render/project/src/app.py\", line 1084, in api_lanzar_orden_motor\n    tid = _disparar_orden_interna(marca, formato, \"\", duracion_min)\n          ^^^^^^^^^^^^^^^^^^^^^^^^^^^^^^^^^^^^^^^^^^^^^^^^^^^^^^^^^\n  File \"/opt/render/project/src/app.py\", line 506, in _disparar_orden_interna\n    raise Exception(resultado[:120])\nException: ERROR CRÍTICO API GEMINI:\n\n"
  },
  {
    "ts": "2026-06-14 09:36:50",
    "donde": "lanzar_orden_motor",
    "error": "Traceback (most recent call last):\n  File \"/opt/render/project/src/app.py\", line 1084, in api_lanzar_orden_motor\n    tid = _disparar_orden_interna(marca, formato, \"\", duracion_min)\n          ^^^^^^^^^^^^^^^^^^^^^^^^^^^^^^^^^^^^^^^^^^^^^^^^^^^^^^^^^\n  File \"/opt/render/project/src/app.py\", line 506, in _disparar_orden_interna\n    raise Exception(resultado[:120])\nException: ERROR CRÍTICO API GEMINI:\n\n"
  },
  {
    "ts": "2026-06-14 09:37:22",
    "donde": "lanzar_orden_motor",
    "error": "Traceback (most recent call last):\n  File \"/opt/render/project/src/app.py\", line 1084, in api_lanzar_orden_motor\n    tid = _disparar_orden_interna(marca, formato, \"\", duracion_min)\n          ^^^^^^^^^^^^^^^^^^^^^^^^^^^^^^^^^^^^^^^^^^^^^^^^^^^^^^^^^\n  File \"/opt/render/project/src/app.py\", line 506, in _disparar_orden_interna\n    raise Exception(resultado[:120])\nException: ERROR CRÍTICO API GEMINI:\n\n"
  },
  {
    "ts": "2026-06-14 09:37:55",
    "donde": "lanzar_orden_motor",
    "error": "Traceback (most recent call last):\n  File \"/opt/render/project/src/app.py\", line 1084, in api_lanzar_orden_motor\n    tid = _disparar_orden_interna(marca, formato, \"\", duracion_min)\n          ^^^^^^^^^^^^^^^^^^^^^^^^^^^^^^^^^^^^^^^^^^^^^^^^^^^^^^^^^\n  File \"/opt/render/project/src/app.py\", line 506, in _disparar_orden_interna\n    raise Exception(resultado[:120])\nException: ERROR CRÍTICO API GEMINI:\n\n"
  },
  {
    "ts": "2026-06-14 09:38:29",
    "donde": "lanzar_orden_motor",
    "error": "Traceback (most recent call last):\n  File \"/opt/render/project/src/app.py\", line 1084, in api_lanzar_orden_motor\n    tid = _disparar_orden_interna(marca, formato, \"\", duracion_min)\n          ^^^^^^^^^^^^^^^^^^^^^^^^^^^^^^^^^^^^^^^^^^^^^^^^^^^^^^^^^\n  File \"/opt/render/project/src/app.py\", line 506, in _disparar_orden_interna\n    raise Exception(resultado[:120])\nException: ERROR CRÍTICO API GEMINI:\n\n"
  },
  {
    "ts": "2026-06-14 09:39:02",
    "donde": "lanzar_orden_motor",
    "error": "Traceback (most recent call last):\n  File \"/opt/render/project/src/app.py\", line 1084, in api_lanzar_orden_motor\n    tid = _disparar_orden_interna(marca, formato, \"\", duracion_min)\n          ^^^^^^^^^^^^^^^^^^^^^^^^^^^^^^^^^^^^^^^^^^^^^^^^^^^^^^^^^\n  File \"/opt/render/project/src/app.py\", line 506, in _disparar_orden_interna\n    raise Exception(resultado[:120])\nException: ERROR CRÍTICO API GEMINI:\n\n"
  },
  {
    "ts": "2026-06-14 09:39:35",
    "donde": "lanzar_orden_motor",
    "error": "Traceback (most recent call last):\n  File \"/opt/render/project/src/app.py\", line 1084, in api_lanzar_orden_motor\n    tid = _disparar_orden_interna(marca, formato, \"\", duracion_min)\n          ^^^^^^^^^^^^^^^^^^^^^^^^^^^^^^^^^^^^^^^^^^^^^^^^^^^^^^^^^\n  File \"/opt/render/project/src/app.py\", line 506, in _disparar_orden_interna\n    raise Exception(resultado[:120])\nException: ERROR CRÍTICO API GEMINI:\n\n"
  },
  {
    "ts": "2026-06-14 09:40:08",
    "donde": "lanzar_orden_motor",
    "error": "Traceback (most recent call last):\n  File \"/opt/render/project/src/app.py\", line 1084, in api_lanzar_orden_motor\n    tid = _disparar_orden_interna(marca, formato, \"\", duracion_min)\n          ^^^^^^^^^^^^^^^^^^^^^^^^^^^^^^^^^^^^^^^^^^^^^^^^^^^^^^^^^\n  File \"/opt/render/project/src/app.py\", line 506, in _disparar_orden_interna\n    raise Exception(resultado[:120])\nException: ERROR CRÍTICO API GEMINI:\n\n"
  },
  {
    "ts": "2026-06-14 09:40:41",
    "donde": "lanzar_orden_motor",
    "error": "Traceback (most recent call last):\n  File \"/opt/render/project/src/app.py\", line 1084, in api_lanzar_orden_motor\n    tid = _disparar_orden_interna(marca, formato, \"\", duracion_min)\n          ^^^^^^^^^^^^^^^^^^^^^^^^^^^^^^^^^^^^^^^^^^^^^^^^^^^^^^^^^\n  File \"/opt/render/project/src/app.py\", line 506, in _disparar_orden_interna\n    raise Exception(resultado[:120])\nException: ERROR CRÍTICO API GEMINI:\n\n"
  },
  {
    "ts": "2026-06-14 09:41:15",
    "donde": "lanzar_orden_motor",
    "error": "Traceback (most recent call last):\n  File \"/opt/render/project/src/app.py\", line 1084, in api_lanzar_orden_motor\n    tid = _disparar_orden_interna(marca, formato, \"\", duracion_min)\n          ^^^^^^^^^^^^^^^^^^^^^^^^^^^^^^^^^^^^^^^^^^^^^^^^^^^^^^^^^\n  File \"/opt/render/project/src/app.py\", line 506, in _disparar_orden_interna\n    raise Exception(resultado[:120])\nException: ERROR CRÍTICO API GEMINI:\n\n"
  },
  {
    "ts": "2026-06-14 09:41:48",
    "donde": "lanzar_orden_motor",
    "error": "Traceback (most recent call last):\n  File \"/opt/render/project/src/app.py\", line 1084, in api_lanzar_orden_motor\n    tid = _disparar_orden_interna(marca, formato, \"\", duracion_min)\n          ^^^^^^^^^^^^^^^^^^^^^^^^^^^^^^^^^^^^^^^^^^^^^^^^^^^^^^^^^\n  File \"/opt/render/project/src/app.py\", line 506, in _disparar_orden_interna\n    raise Exception(resultado[:120])\nException: ERROR CRÍTICO API GEMINI:\n\n"
  },
  {
    "ts": "2026-06-14 09:42:21",
    "donde": "lanzar_orden_motor",
    "error": "Traceback (most recent call last):\n  File \"/opt/render/project/src/app.py\", line 1084, in api_lanzar_orden_motor\n    tid = _disparar_orden_interna(marca, formato, \"\", duracion_min)\n          ^^^^^^^^^^^^^^^^^^^^^^^^^^^^^^^^^^^^^^^^^^^^^^^^^^^^^^^^^\n  File \"/opt/render/project/src/app.py\", line 506, in _disparar_orden_interna\n    raise Exception(resultado[:120])\nException: ERROR CRÍTICO API GEMINI:\n\n"
  },
  {
    "ts": "2026-06-14 09:42:54",
    "donde": "lanzar_orden_motor",
    "error": "Traceback (most recent call last):\n  File \"/opt/render/project/src/app.py\", line 1084, in api_lanzar_orden_motor\n    tid = _disparar_orden_interna(marca, formato, \"\", duracion_min)\n          ^^^^^^^^^^^^^^^^^^^^^^^^^^^^^^^^^^^^^^^^^^^^^^^^^^^^^^^^^\n  File \"/opt/render/project/src/app.py\", line 506, in _disparar_orden_interna\n    raise Exception(resultado[:120])\nException: ERROR CRÍTICO API GEMINI:\n\n"
  },
  {
    "ts": "2026-06-14 09:43:27",
    "donde": "lanzar_orden_motor",
    "error": "Traceback (most recent call last):\n  File \"/opt/render/project/src/app.py\", line 1084, in api_lanzar_orden_motor\n    tid = _disparar_orden_interna(marca, formato, \"\", duracion_min)\n          ^^^^^^^^^^^^^^^^^^^^^^^^^^^^^^^^^^^^^^^^^^^^^^^^^^^^^^^^^\n  File \"/opt/render/project/src/app.py\", line 506, in _disparar_orden_interna\n    raise Exception(resultado[:120])\nException: ERROR CRÍTICO API GEMINI:\n\n"
  },
  {
    "ts": "2026-06-14 09:44:01",
    "donde": "lanzar_orden_motor",
    "error": "Traceback (most recent call last):\n  File \"/opt/render/project/src/app.py\", line 1084, in api_lanzar_orden_motor\n    tid = _disparar_orden_interna(marca, formato, \"\", duracion_min)\n          ^^^^^^^^^^^^^^^^^^^^^^^^^^^^^^^^^^^^^^^^^^^^^^^^^^^^^^^^^\n  File \"/opt/render/project/src/app.py\", line 506, in _disparar_orden_interna\n    raise Exception(resultado[:120])\nException: ERROR CRÍTICO API GEMINI:\n\n"
  }
]